opustools/__init__.py
opustools/old_opus_langid.py
opustools/opus_cat.py
opustools/opus_filter.py
opustools/opus_get.py
opustools/opus_langid.py
opustools/opus_read.py
opustools/util.py
opustools/filter/__init__.py
opustools/filter/lm.py
opustools/filter/pipeline.py
opustools/filter/tokenization.py
opustools/filter/word_alignment.py
opustools/parse/__init__.py
opustools/parse/alignment_parser.py
opustools/parse/exhaustive_sentence_parser.py
opustools/parse/links_alignment_parser.py
opustools/parse/moses_read.py
opustools/parse/sentence_parser.py
opustools_pkg/__init__.py
opustools_pkg/old_opus_langid.py
opustools_pkg/opus_cat.py
opustools_pkg/opus_filter.py
opustools_pkg/opus_get.py
opustools_pkg/opus_langid.py
opustools_pkg/opus_read.py
opustools_pkg/util.py
opustools_pkg/filter/__init__.py
opustools_pkg/filter/alignment.py
opustools_pkg/filter/alignment_reader.py
opustools_pkg/filter/alignment_writer.py
opustools_pkg/filter/lm.py
opustools_pkg/filter/pipeline.py
opustools_pkg/filter/tokenization.py
opustools_pkg/filter/word_alignment.py
opustools_pkg/filter/tests/20180518.py
opustools_pkg/filter/tests/__init__.py
opustools_pkg/parse/__init__.py
opustools_pkg/parse/alignment_parser.py
opustools_pkg/parse/exhaustive_sentence_parser.py
opustools_pkg/parse/links_alignment_parser.py
opustools_pkg/parse/moses_read.py
opustools_pkg/parse/sentence_parser.py
opustools_pkg-0.0.52.data/scripts/opus_cat
opustools_pkg-0.0.52.data/scripts/opus_express
opustools_pkg-0.0.52.data/scripts/opus_filter
opustools_pkg-0.0.52.data/scripts/opus_get
opustools_pkg-0.0.52.data/scripts/opus_langid
opustools_pkg-0.0.52.data/scripts/opus_read
opustools_pkg-0.0.52.dist-info/LICENSE
opustools_pkg-0.0.52.dist-info/METADATA
opustools_pkg-0.0.52.dist-info/WHEEL
opustools_pkg-0.0.52.dist-info/top_level.txt
opustools_pkg-0.0.52.dist-info/RECORD
