Metadata-Version: 2.1
Name: opustools-pkg
Version: 0.0.52
Summary: Tools to read OPUS
Home-page: https://github.com/Helsinki-NLP/OpusTools
Author: Mikko Aulamo
Author-email: mikko.aulamo@helsinki.fi
License: UNKNOWN
Platform: UNKNOWN
Classifier: Programming Language :: Python :: 3
Classifier: License :: OSI Approved :: MIT License
Classifier: Operating System :: OS Independent
